{"AccessControlPolicy":{"Owner":{"DisplayName":"","ID":"","XMLName":{"Space":"","Local":""}},"Delivered":"","Grants":null,"XMLName":{"Space":"","Local":""}},"BucketEncryptionConfiguration":{"SSEAlgorithm":"","ProjectID":"","KMSMasterKeyID":"","XMLName":{"Space":"","Local":""}},"BucketPolicy":"","Bucket":{"CreationDate":"xcWSJ5kZ1M5U2kGXfsSXnf9q","BucketType":"4hY3cc","Location":"","Name":"p7j5vlgEH60I47zZa6MUzjYmCSyeMiq","XMLName":{"Space":"4yte2pbJbuxeKcdi4JoxOPfilYyeH2g46eoDfwPmb","Local":"wF8UM7"}}}