{"SecurityGroup":[{"Outbound":[{"CidrIp":"7yBm2j4Fz","Desc":"","Action":"HE4592","PortRange":"oOc","AddressModule":"","IpProtocol":"QfQ","Dir":""}],"SecurityGroupName":"VIBeKWP8Cyj1o","SecurityGroupRemark":"JPo","CreateTime":"LmA0bvxdgYEPPrNWkhI","SecurityGroupId":"GVww3jCuKyL","ProjectId":0,"Inbound":[{"CidrIp":"6ShccA1w9ca7pc","Desc":"LDSOaYqB3BX","Action":"55P8","PortRange":"Y2q7","AddressModule":"","IpProtocol":"cEp","Dir":""},{"CidrIp":"lV0lF8Uc3JEz84","Desc":"bSbLYmFIlfA","Action":"zgL3","PortRange":"bocJ","AddressModule":"","IpProtocol":"n4Q","Dir":""},{"CidrIp":"PcLWf3F0PwdcgF","Desc":"2vT7U0ZUVYF","Action":"Xmvb","PortRange":"q4ay","AddressModule":"","IpProtocol":"UYB","Dir":""},{"CidrIp":"T4G6vI49jCUxvU","Desc":"P94JCNRXQZ","Action":"rfwpbQ","PortRange":"rP2D","AddressModule":"","IpProtocol":"raN","Dir":""},{"CidrIp":"Gojs7Ta0Y6hlK","Desc":"oSsU7AeOE","Action":"3GleLM","PortRange":"Ln7R","AddressModule":"","IpProtocol":"kjE","Dir":""},{"CidrIp":"EXmCKeOUDio5SiK","Desc":"i777f7s3OAm","Action":"fBfppi","PortRange":"EENv","AddressModule":"","IpProtocol":"mKw","Dir":""},{"CidrIp":"rRGK53NJoqyj","Desc":"vzMsLkjX","Action":"c0jf9h","PortRange":"SuXPw7T3q","AddressModule":"","IpProtocol":"Za9","Dir":""},{"CidrIp":"hZtVMN9lukhyc","Desc":"ZRW41ZJaOhobRD","Action":"LpTHHW","PortRange":"ATM","AddressModule":"","IpProtocol":"mNB","Dir":""},{"CidrIp":"daJPyY3UM45j","Desc":"","Action":"ygqfPQ","PortRange":"4OSPoItfO","AddressModule":"","IpProtocol":"JDZ","Dir":""},{"CidrIp":"kFIvUFpSJhbW","Desc":"YIJFrYr7eChtGKL83ND0l","Action":"QE7bIA","PortRange":"LqQZ","AddressModule":"","IpProtocol":"ULp","Dir":""},{"CidrIp":"XBIahwEvnQNVy","Desc":"p8aR5R5QNdhv","Action":"jPgOIP","PortRange":"0XX","AddressModule":"","IpProtocol":"Psd","Dir":""},{"CidrIp":"LClSLQSchDPmTQJ","Desc":"VefY8ArBOAzNu0XvYu7GvFi","Action":"VKPsPv","PortRange":"UNbYDxgKi","AddressModule":"","IpProtocol":"wmU","Dir":""},{"CidrIp":"ds2ltaTe9FO9V1","Desc":"mvRxKsCIVSQBJEl8m2X68dU","Action":"w1IW8x","PortRange":"dLPDdVmZ7","AddressModule":"","IpProtocol":"86W","Dir":""},{"CidrIp":"5IZ3YcRUhXlm","Desc":"wAdmAKtaxa0hRkjJxvpWS4j","Action":"mA0tvU","PortRange":"6vRdq1GKu","AddressModule":"","IpProtocol":"xdT","Dir":""},{"CidrIp":"bwjHWBsGpEMNC","Desc":"CDNmdlGeLb7tTHGL4SABJiJ","Action":"fRizfC","PortRange":"uHcmYxdN5","AddressModule":"","IpProtocol":"0jB","Dir":""},{"CidrIp":"xmurjFV1yHsr5","Desc":"HKeRyeC9pfdgwzyax59o0Et","Action":"cYvMnZ","PortRange":"KXzsgqOX9","AddressModule":"","IpProtocol":"RAh","Dir":""},{"CidrIp":"DNwRASqBkmEe10","Desc":"ecUggI3tGEn0MMHniY6ObiO","Action":"4KxQKs","PortRange":"50tulNJnh","AddressModule":"","IpProtocol":"Nwj","Dir":""},{"CidrIp":"41TUzEpeSDUc1","Desc":"dmHqNo70twq3A9RJt87DXRd","Action":"lPFcGv","PortRange":"y7t3yFHfX","AddressModule":"","IpProtocol":"g0J","Dir":""},{"CidrIp":"tKWvf0RrRAKP3","Desc":"DMtYiLses5i9RzQr4Dk4r4M","Action":"3AKr58","PortRange":"L8QQXNH6t","AddressModule":"","IpProtocol":"W5u","Dir":""},{"CidrIp":"vhU68RMkaG1KGC","Desc":"7OD0UE23kSS4kfdUzVGqVmG","Action":"i1uKPE","PortRange":"iH42az9k6","AddressModule":"","IpProtocol":"kRb","Dir":""},{"CidrIp":"FzZYUkB1xJGQM","Desc":"LSU4fONurdW1VoEDMgTqH","Action":"7zjJpv","PortRange":"ibQbDcKoSSe9Go","AddressModule":"","IpProtocol":"3hO","Dir":""},{"CidrIp":"SVHmWeVLXwVa","Desc":"urYakMYmwxxBfox2eGs1u","Action":"thl0S1","PortRange":"Yl","AddressModule":"","IpProtocol":"Ovd","Dir":""},{"CidrIp":"oDKiAi3sJUtY","Desc":"dTsB5Q7c01k4hYYFdl4fvRtKQ1Nm3","Action":"1mYy0Z","PortRange":"ek39","AddressModule":"","IpProtocol":"Ltg","Dir":""},{"CidrIp":"QmvuUZKHfRvK","Desc":"JdoYIjAMZzOZjiqTF8cT","Action":"f9uGZl","PortRange":"Qyc","AddressModule":"","IpProtocol":"Wjh3","Dir":""},{"CidrIp":"ufeMM2mieQscQ","Desc":"26a8926gIzzGZpFi","Action":"XPPUVg","PortRange":"XOi","AddressModule":"","IpProtocol":"TZ0d","Dir":""}]}],"AuditConfig":null,"InstanceInfo":{"DeviceClass":"","Memory":4000,"AutoRenew":0,"Cpu":2,"SubnetId":4728995,"DeployGroupId":"","DiskType":"","UniqSubnetId":"QvLLysiNNdBVSrq","ZoneName":"","DeployMode":1,"Qps":4400,"EngineType":"tPwxu2","PhysicalId":"","InstanceType":1,"CdbError":0,"WanPort":0,"ProtectMode":0,"Status":1,"EngineVersion":"5AB","ZoneId":100003,"InstanceId":"vii0eEBUMGxB","WanStatus":0,"Zone":"3zaLZXle0aTomX","CreateTime":"SuntU0aHo3xsEgcAnd9","Vport":3306,"InitFlag":1,"ProjectId":0,"PayType":1,"TaskStatus":0,"UniqVpcId":"tLJtuUFAROmZ","InstanceName":"LrtaBOFpx2iGdTff","DeviceType":"dphRjSqbF","WanDomain":"","MaxDelayTime":0,"VpcId":8260424,"ExpandCpu":0,"Volume":100,"DeadlineTime":"gKuyCzIpVvCPIBZT7FI","Region":"S0FvHuklgaZd","InstanceNodes":2,"SlaveInfo":{"First":{"Zone":"mhMnvk28tG8uFg","Vport":0,"Region":"dhijKkhUIowZ","Vip":""}},"Vip":"ooGiqbSCkWc"}}